cacao_password/__init__.py
cacao_password/cli.py
cacao_password/config.py
cacao_password/core.py
cacao_password/gui.py
cacao_password-1.0.1.dist-info/METADATA
cacao_password-1.0.1.dist-info/WHEEL
cacao_password-1.0.1.dist-info/entry_points.txt
cacao_password-1.0.1.dist-info/licenses/LICENSE
cacao_password-1.0.1.dist-info/RECORD
