Metadata-Version: 2.4
Name: cacao-password
Version: 1.0.1
Summary: A secure password generator with brown-themed GUI and CLI interfaces
Project-URL: Homepage, https://github.com/cacao-research/cacao-password
Project-URL: Bug Reports, https://github.com/cacao-research/cacao-password/issues
Project-URL: Source, https://github.com/cacao-research/cacao-password
Author-email: Juan Denis <juan@vene.co>
License: MIT License
License-File: LICENSE
Keywords: cli,generator,gui,password,security
Classifier: Development Status :: 5 - Production/Stable
Classifier: Intended Audience :: End Users/Desktop
Classifier: License :: OSI Approved :: MIT License
Classifier: Operating System :: OS Independent
Classifier: Programming Language :: Python :: 3
Classifier: Programming Language :: Python :: 3.8
Classifier: Programming Language :: Python :: 3.9
Classifier: Programming Language :: Python :: 3.10
Classifier: Programming Language :: Python :: 3.11
Classifier: Programming Language :: Python :: 3.12
Classifier: Topic :: Security :: Cryptography
Classifier: Topic :: Utilities
Requires-Python: >=3.8
Requires-Dist: cacao-password-generator
Provides-Extra: dev
Requires-Dist: black; extra == 'dev'
Requires-Dist: flake8; extra == 'dev'
Requires-Dist: mypy; extra == 'dev'
Requires-Dist: pytest; extra == 'dev'
